Metadata-Version: 2.1
Name: medeiroscalculator
Version: 0.0.1
Summary: A very basic calculator
Home-page: 
Author: Gustavo Medeiros
Author-email: gustavomedeirosstemis@gmail.com
License: MIT
Keywords: calculator
Classifier: Development Status :: 5 - Production/Stable
Classifier: Intended Audience :: Education
Classifier: Operating System :: Microsoft :: Windows :: Windows 10
Classifier: Operating System :: POSIX :: Linux
Classifier: Operating System :: OS Independent
Classifier: License :: OSI Approved :: MIT License
Classifier: Programming Language :: Python :: 3
License-File: LICENCE.txt
